kernelmind/__init__.py
kernelmind/core.py
kernelmind-0.1.1.dist-info/licenses/LICENSE
kernelmind-0.1.1.dist-info/METADATA
kernelmind-0.1.1.dist-info/WHEEL
kernelmind-0.1.1.dist-info/top_level.txt
kernelmind-0.1.1.dist-info/RECORD
