Metadata-Version: 2.4
Name: kernelmind
Version: 0.1.1
Summary: A minimalist thinking kernel for LLM agents
Home-page: https://github.com/zhanj/kernelmind-framework
Author: Ethan Zhan
Author-email: Ethan Zhan <jiezhan1@gmail.com>
License: MIT
Project-URL: Homepage, https://github.com/zhanj/kernelmind-framework
Project-URL: Repository, https://github.com/zhanj/kernelmind-framework
Project-URL: Documentation, https://github.com/zhanj/kernelmind-framework#readme
Project-URL: Issues, https://github.com/zhanj/kernelmind-framework/issues
Keywords: ai,agents,llm,workflow,framework
Classifier: Development Status :: 3 - Alpha
Classifier: Intended Audience :: Developers
Classifier: License :: OSI Approved :: MIT License
Classifier: Programming Language :: Python :: 3
Classifier: Programming Language :: Python :: 3.8
Classifier: Programming Language :: Python :: 3.9
Classifier: Programming Language :: Python :: 3.10
Classifier: Programming Language :: Python :: 3.11
Classifier: Programming Language :: Python :: 3.12
Classifier: Programming Language :: Python :: 3.13
Classifier: Topic :: Software Development :: Libraries :: Python Modules
Classifier: Topic :: Scientific/Engineering :: Artificial Intelligence
Requires-Python: >=3.8
License-File: LICENSE
Requires-Dist: openai>=1.0.0
Requires-Dist: pyyaml>=6.0
Requires-Dist: numpy>=1.21.0
Requires-Dist: setuptools>=75.3.2
Provides-Extra: dev
Requires-Dist: pytest>=7.0.0; extra == "dev"
Requires-Dist: pytest-cov>=4.0.0; extra == "dev"
Requires-Dist: black>=23.0.0; extra == "dev"
Requires-Dist: isort>=5.0.0; extra == "dev"
Requires-Dist: flake8>=6.0.0; extra == "dev"
Provides-Extra: test
Requires-Dist: pytest>=7.0.0; extra == "test"
Requires-Dist: pytest-cov>=4.0.0; extra == "test"
Dynamic: author
Dynamic: home-page
Dynamic: license-file
Dynamic: requires-python
